libLemon/__init__.py
libLemon/ASM/__init__.py
libLemon/ASM/Delegate/ParamDelegate.py
libLemon/ASM/Delegate/__init__.py
libLemon/ASM/Entity/ASMMain.py
libLemon/ASM/Entity/Kernel.py
libLemon/ASM/Entity/Layer.py
libLemon/ASM/Entity/Parameter.py
libLemon/ASM/Entity/State.py
libLemon/ASM/Entity/Transition.py
libLemon/ASM/Entity/__init__.py
libLemon/ASM/Message/ParamGetRequestMessage.py
libLemon/ASM/Message/ParamGetResponseMessage.py
libLemon/ASM/Message/ParamSetRequestMessage.py
libLemon/ASM/Message/ParamSetResponseMessage.py
libLemon/ASM/Message/ScheduleRequestMessage.py
libLemon/ASM/Message/ScheduleResponseMessage.py
libLemon/ASM/Message/YieldMessage.py
libLemon/ASM/Message/__init__.py
libLemon/ASM/Parse/Parse.py
libLemon/ASM/Parse/__init__.py
libLemon/Error/Error.py
libLemon/Error/__init__.py
libLemon/MTP/EMQ.py
libLemon/MTP/Messenger.py
libLemon/MTP/Payload.py
libLemon/MTP/__init__.py
libLemon/Utils/Args.py
libLemon/Utils/Const.py
libLemon/Utils/Logger.py
libLemon/Utils/Runner.py
libLemon/Utils/Sleep.py
libLemon/Utils/Utilities.py
libLemon/Utils/__init__.py
libLemon-0.0.3.dist-info/LICENSE
libLemon-0.0.3.dist-info/METADATA
libLemon-0.0.3.dist-info/WHEEL
libLemon-0.0.3.dist-info/top_level.txt
libLemon-0.0.3.dist-info/RECORD
